gtfsr_kit/__init__.py
gtfsr_kit/main.py
gtfsr_kit-7.0.1.dist-info/LICENSE.txt
gtfsr_kit-7.0.1.dist-info/WHEEL
gtfsr_kit-7.0.1.dist-info/METADATA
gtfsr_kit-7.0.1.dist-info/RECORD
